solid2/__init__.py
solid2/config.py
solid2/core/__init__.py
solid2/core/builtins/__init__.py
solid2/core/builtins/convenience.py
solid2/core/builtins/implicit.primitives
solid2/core/builtins/openscad.mutators
solid2/core/builtins/openscad.primitives
solid2/core/builtins/openscad_functions.py
solid2/core/builtins/openscad_primitives.py
solid2/core/builtins/primitives.py
solid2/core/extension_manager.py
solid2/core/object_base/__init__.py
solid2/core/object_base/access_syntax_mixin.py
solid2/core/object_base/object_base_impl.py
solid2/core/object_base/operator_mixin.py
solid2/core/object_factory.py
solid2/core/parse_scad.py
solid2/core/scad_import.py
solid2/core/scad_render.py
solid2/core/utils.py
solid2/examples/01-basics.py
solid2/examples/01-basics.scad
solid2/examples/02-vars-and-operators.py
solid2/examples/02-vars-and-operators.scad
solid2/examples/03-debug-background.py
solid2/examples/03-debug-background.scad
solid2/examples/04-convenience.py
solid2/examples/04-convenience.scad
solid2/examples/05-access-style-syntax.py
solid2/examples/05-access-style-syntax.scad
solid2/examples/06-functions.py
solid2/examples/06-functions.scad
solid2/examples/07-libs-bosl2-attachable.py
solid2/examples/07-libs-bosl2-attachable.scad
solid2/examples/07-libs-bosl2-logo.py
solid2/examples/07-libs-bosl2-logo.scad
solid2/examples/07-libs-bosl2.py
solid2/examples/07-libs-bosl2.scad
solid2/examples/07-libs.x.py
solid2/examples/08-extensions.py
solid2/examples/08-extensions.scad
solid2/examples/09-code-attach-extension.py
solid2/examples/09-code-attach-extension.scad
solid2/examples/10-customizer.py
solid2/examples/10-customizer.scad
solid2/examples/11-font/LICENSE_README
solid2/examples/11-font/RichEatin.otf
solid2/examples/11-fonts.x.py
solid2/examples/12-animation.py
solid2/examples/12-animation.scad
solid2/examples/13-animated-bouncing-ball.py
solid2/examples/13-animated-bouncing-ball.scad
solid2/examples/14-implicitCAD.x.py
solid2/examples/15-implicitCAD2.x.py
solidpython2-2.1.2.dist-info/METADATA
solidpython2-2.1.2.dist-info/WHEEL
solidpython2-2.1.2.dist-info/RECORD
