Metadata-Version: 2.1
Name: solidpython2
Version: 2.1.2
Summary: Python interface to the OpenSCAD declarative geometry language
Home-page: https://github.com/jeff-dh/SolidPython
License: LGPL-2.1
Keywords: 3D,CAD,CSG,constructive solid geometry,geometry,modeling,OpenSCAD
Author: jeff
Requires-Python: >=3.7
Classifier: Development Status :: 4 - Beta
Classifier: Environment :: Other Environment
Classifier: Intended Audience :: Developers
Classifier: License :: OSI Approved
Classifier: License :: OSI Approved :: GNU Lesser General Public License v2 or later (LGPLv2+)
Classifier: Operating System :: OS Independent
Classifier: Programming Language :: Python
Classifier: Programming Language :: Python :: 3
Classifier: Programming Language :: Python :: 3.7
Classifier: Programming Language :: Python :: 3.8
Classifier: Programming Language :: Python :: 3.9
Classifier: Programming Language :: Python :: 3.10
Classifier: Programming Language :: Python :: 3.11
Classifier: Programming Language :: Python :: 3.12
Classifier: Programming Language :: Python :: 3.13
Classifier: Topic :: Scientific/Engineering :: Mathematics
Classifier: Topic :: Software Development :: Libraries :: Python Modules
Requires-Dist: ply (>=3.11,<4.0)
Requires-Dist: setuptools (>=65.6.3)
Project-URL: Repository, https://github.com/jeff-dh/SolidPython
